<vector android:autoMirrored="true" android:height="40dp"
    android:viewportHeight="40" android:viewportWidth="40"
    android:width="40dp" xmlns:aapt="http://schemas.android.com/aapt" xmlns:android="http://schemas.android.com/apk/res/android">
    <path android:pathData="M33.333,6.667H6.667C4.833,6.667 3.35,8.167 3.35,10L3.333,30C3.333,31.833 4.833,33.333 6.667,33.333H33.333C35.167,33.333 36.667,31.833 36.667,30V10C36.667,8.167 35.167,6.667 33.333,6.667ZM32.667,13.75L20.883,21.117C20.35,21.45 19.65,21.45 19.117,21.117L7.333,13.75C7.166,13.656 7.02,13.53 6.903,13.377C6.786,13.225 6.702,13.051 6.654,12.866C6.607,12.68 6.597,12.487 6.627,12.297C6.656,12.108 6.724,11.926 6.825,11.764C6.927,11.601 7.06,11.461 7.218,11.352C7.375,11.242 7.553,11.166 7.741,11.127C7.928,11.089 8.122,11.088 8.31,11.127C8.498,11.165 8.676,11.241 8.833,11.35L20,18.333L31.167,11.35C31.324,11.241 31.502,11.165 31.69,11.127C31.878,11.088 32.071,11.089 32.259,11.127C32.447,11.166 32.625,11.242 32.782,11.352C32.939,11.461 33.073,11.601 33.174,11.764C33.276,11.926 33.344,12.108 33.373,12.297C33.402,12.487 33.393,12.68 33.346,12.866C33.298,13.051 33.214,13.225 33.097,13.377C32.98,13.53 32.834,13.656 32.667,13.75Z">
        <aapt:attr name="android:fillColor">
            <gradient android:endX="41.313" android:endY="12.385"
                android:startX="3.333" android:startY="5.029" android:type="linear">
                <item android:color="#FF53E88B" android:offset="0"/>
                <item android:color="#FF15BE77" android:offset="1"/>
            </gradient>
        </aapt:attr>
    </path>
</vector>
